discrete_opt/__init__.py
discrete_opt/optimization.py
discrete_opt/util.py
discrete_opt-0.1.dist-info/DESCRIPTION.rst
discrete_opt-0.1.dist-info/METADATA
discrete_opt-0.1.dist-info/RECORD
discrete_opt-0.1.dist-info/WHEEL
discrete_opt-0.1.dist-info/metadata.json
discrete_opt-0.1.dist-info/top_level.txt
