Metadata-Version: 2.0
Name: discrete-opt
Version: 0.1
Summary: Provides methods to minimize scalar and multivariate functions of discrete (integer) variables.
Home-page: http://github.com/claudiofahey/discrete_opt
Author: Claudio Fahey
Author-email: claudiofahey@gmail.com
License: MIT
Platform: UNKNOWN
Requires-Dist: numpy
Requires-Dist: scipy
